{"cameraMode":{"drawMode":0,"name":"Shaded","section":"Shading Mode"},"sceneLighting":true,"audioPlay":false,"sceneViewState":{"showFog":true,"showMaterialUpdate":false,"showSkybox":true,"showFlares":true,"showImageEffects":true,"showParticleSystems":true},"in2DMode":false,"pivot":{"x":-5.784510612487793,"y":-4.996692180633545,"z":1.4064862728118897},"rotation":{"x":-0.2822774052619934,"y":0.5492901802062988,"z":-0.2041315883398056,"w":-0.7595765590667725},"size":11.092366218566895,"orthographic":false}